brainbase_labs/__init__.py
brainbase_labs/_base_client.py
brainbase_labs/_client.py
brainbase_labs/_compat.py
brainbase_labs/_constants.py
brainbase_labs/_exceptions.py
brainbase_labs/_files.py
brainbase_labs/_models.py
brainbase_labs/_qs.py
brainbase_labs/_resource.py
brainbase_labs/_response.py
brainbase_labs/_streaming.py
brainbase_labs/_types.py
brainbase_labs/_version.py
brainbase_labs/py.typed
brainbase_labs/_utils/__init__.py
brainbase_labs/_utils/_compat.py
brainbase_labs/_utils/_datetime_parse.py
brainbase_labs/_utils/_json.py
brainbase_labs/_utils/_logs.py
brainbase_labs/_utils/_proxy.py
brainbase_labs/_utils/_reflection.py
brainbase_labs/_utils/_resources_proxy.py
brainbase_labs/_utils/_streams.py
brainbase_labs/_utils/_sync.py
brainbase_labs/_utils/_transform.py
brainbase_labs/_utils/_typing.py
brainbase_labs/_utils/_utils.py
brainbase_labs/lib/.keep
brainbase_labs/resources/__init__.py
brainbase_labs/resources/portkey_logs.py
brainbase_labs/resources/voice_analysis.py
brainbase_labs/resources/team/__init__.py
brainbase_labs/resources/team/assets.py
brainbase_labs/resources/team/custom_voices.py
brainbase_labs/resources/team/default_checks.py
brainbase_labs/resources/team/team.py
brainbase_labs/resources/team/integrations/__init__.py
brainbase_labs/resources/team/integrations/integrations.py
brainbase_labs/resources/team/integrations/twilio.py
brainbase_labs/resources/workers/__init__.py
brainbase_labs/resources/workers/business_hours.py
brainbase_labs/resources/workers/flows.py
brainbase_labs/resources/workers/folders.py
brainbase_labs/resources/workers/runtime_errors.py
brainbase_labs/resources/workers/sessions.py
brainbase_labs/resources/workers/team_phone_hours.py
brainbase_labs/resources/workers/tests.py
brainbase_labs/resources/workers/workers.py
brainbase_labs/resources/workers/deployment_logs/__init__.py
brainbase_labs/resources/workers/deployment_logs/deployment_logs.py
brainbase_labs/resources/workers/deployment_logs/sms.py
brainbase_labs-7.12.0.dist-info/METADATA
brainbase_labs-7.12.0.dist-info/WHEEL
brainbase_labs-7.12.0.dist-info/licenses/LICENSE
brainbase_labs-7.12.0.dist-info/RECORD
